napari_orthogonal_views/__init__.py
napari_orthogonal_views/_version.py
napari_orthogonal_views/cross_hair_overlay.py
napari_orthogonal_views/napari.yaml
napari_orthogonal_views/ortho_view_manager.py
napari_orthogonal_views/ortho_view_widget.py
napari_orthogonal_views/widget_controls.py
napari_orthogonal_views/_tests/__init__.py
napari_orthogonal_views/_tests/test_ortho_view_manager.py
napari_orthogonal_views/_tests/test_ortho_view_widget.py
napari_orthogonal_views-0.1.0.dist-info/licenses/LICENSE
napari_orthogonal_views-0.1.0.dist-info/METADATA
napari_orthogonal_views-0.1.0.dist-info/WHEEL
napari_orthogonal_views-0.1.0.dist-info/entry_points.txt
napari_orthogonal_views-0.1.0.dist-info/top_level.txt
napari_orthogonal_views-0.1.0.dist-info/RECORD
