Metadata-Version: 2.4
Name: napari-orthogonal-views
Version: 0.1.0
Summary: A napari plugin for dynamically displaying orthogonal views and syncing events between the different viewers.
Author: Anniek Stokkermans
Author-email: anniek.stokkermans@gmail.com
License: 
Project-URL: Homepage, https://github.com/AnniekStok/napari-orthogonal-views
Project-URL: Issues, https://github.com/AnniekStok/napari-orthogonal-views/issues
Classifier: Development Status :: 2 - Pre-Alpha
Classifier: Framework :: napari
Classifier: Intended Audience :: Developers
Classifier: License :: OSI Approved :: BSD License
Classifier: Operating System :: OS Independent
Classifier: Programming Language :: Python
Classifier: Programming Language :: Python :: 3
Classifier: Programming Language :: Python :: 3 :: Only
Classifier: Programming Language :: Python :: 3.10
Classifier: Programming Language :: Python :: 3.11
Classifier: Programming Language :: Python :: 3.12
Classifier: Programming Language :: Python :: 3.13
Classifier: Topic :: Scientific/Engineering :: Image Processing
Requires-Python: >=3.10
License-File: LICENSE
Requires-Dist: napari<1,>=0.5
Requires-Dist: numpy
Requires-Dist: qtpy
Provides-Extra: all
Requires-Dist: napari[all]; extra == "all"
Provides-Extra: testing
Requires-Dist: tox; extra == "testing"
Requires-Dist: pytest; extra == "testing"
Requires-Dist: pytest-cov; extra == "testing"
Requires-Dist: pytest-qt; extra == "testing"
Requires-Dist: napari[qt]; extra == "testing"
Dynamic: license-file
